narremgen/__init__.py
narremgen/__main__.py
narremgen/analyzestats.py
narremgen/chapters.py
narremgen/data.py
narremgen/export.py
narremgen/gui.py
narremgen/llmcore.py
narremgen/main.py
narremgen/narratives.py
narremgen/pipeline.py
narremgen/segmenter.py
narremgen/themes.py
narremgen/utils.py
narremgen/variants.py
narremgen/data/Advice_Urban_Walk.csv
narremgen/data/Context_Urban_Walk.csv
narremgen/data/Mapping_Urban_Walk.csv
narremgen/data/merged_walk in the city.txt
narremgen/settings/DE.csv
narremgen/settings/SN.csv
narremgen/settings/SN_extended_raw.csv
narremgen/settings/examples.txt
narremgen/settings/examples_untaggued.txt
narremgen/settings/narremgen_gui.ini
narremgen/settings/narremgen_ui.ini
narremgen/settings/narremgen_variants.ini
narremgen/settings/operators_structural_raw.csv
narremgen/settings/operators_stylistic_raw.csv
narremgen/settings/prompt_direct_variant_example.txt
narremgen/settings/prompt_formal_variant_example.txt
narremgen/settings/style.txt
narremgen-0.9.5.dist-info/licenses/LICENSE
narremgen-0.9.5.dist-info/METADATA
narremgen-0.9.5.dist-info/WHEEL
narremgen-0.9.5.dist-info/entry_points.txt
narremgen-0.9.5.dist-info/top_level.txt
narremgen-0.9.5.dist-info/RECORD
