Metadata-Version: 2.4
Name: narremgen
Version: 0.9.5
Summary: Generate artificial structured advice micro-texts from narrative, emotional, and world-context templates.
License-Expression: MIT
Project-URL: Homepage, https://github.com/narremgen
Project-URL: Repository, https://github.com/narremgen/narremgen
Project-URL: Issues, https://github.com/narremgen/narremgen/issues
Requires-Python: >=3.10
License-File: LICENSE
Requires-Dist: requests
Requires-Dist: pandas
Requires-Dist: numpy
Requires-Dist: openai>=1.0.0
Requires-Dist: google-genai>=1.0.0
Provides-Extra: emotions
Requires-Dist: transformers>=4.40; extra == "emotions"
Requires-Dist: torch; extra == "emotions"
Requires-Dist: vaderSentiment; extra == "emotions"
Provides-Extra: textstats
Requires-Dist: lexicalrichness; extra == "textstats"
Provides-Extra: plots
Requires-Dist: matplotlib; extra == "plots"
Provides-Extra: gui
Provides-Extra: all
Requires-Dist: transformers>=4.40; extra == "all"
Requires-Dist: torch; extra == "all"
Requires-Dist: google-genai>=1.0.0; extra == "all"
Requires-Dist: openai>=1.0.0; extra == "all"
Requires-Dist: lexicalrichness; extra == "all"
Requires-Dist: matplotlib; extra == "all"
Requires-Dist: vaderSentiment; extra == "all"
Requires-Dist: python-docx; extra == "all"
Requires-Dist: reportlab; extra == "all"
Dynamic: license-file
